cassinyspawner/__init__.py
cassinyspawner/swarmspawner.py
swarmspawner-0.1.0.dist-info/DESCRIPTION.rst
swarmspawner-0.1.0.dist-info/METADATA
swarmspawner-0.1.0.dist-info/RECORD
swarmspawner-0.1.0.dist-info/WHEEL
swarmspawner-0.1.0.dist-info/metadata.json
swarmspawner-0.1.0.dist-info/top_level.txt
