Metadata-Version: 2.0
Name: swarmspawner
Version: 0.1.0
Summary: 
Home-page: https://github.com/cassinyio/SwarmSpawner
Author: Christian Barra
Author-email: info@cassiny.io
License: BSD
Keywords: Interactive,Interpreter,Shell,Web
Platform: UNKNOWN
Classifier: Development Status :: 3 - Alpha
Classifier: Intended Audience :: Developers
Classifier: Topic :: Software Development :: Libraries :: Python Modules
Classifier: License :: OSI Approved :: BSD License
Classifier: Programming Language :: Python :: 3.3
Classifier: Programming Language :: Python :: 3.4
Classifier: Programming Language :: Python :: 3.5
Classifier: Programming Language :: Python :: 3.6
Requires-Dist: docker (>=2.0.2)
Requires-Dist: jupyterhub (>=0.7.2)
